export_to_csv_lib/__init__.py
export_to_csv_lib/exporter.py
export_to_csv_lib-0.1.dist-info/licenses/LICENSE
export_to_csv_lib-0.1.dist-info/METADATA
export_to_csv_lib-0.1.dist-info/WHEEL
export_to_csv_lib-0.1.dist-info/top_level.txt
export_to_csv_lib-0.1.dist-info/RECORD
