Metadata-Version: 2.4
Name: export_to_csv_lib
Version: 0.1
Summary: This is python library to export the table data to csv.
Home-page: 
Author: Vivek
Author-email:  x23324902@student.ncirl.ie
Keywords: export_to_csv_lib
Classifier: Intended Audience :: Education
Classifier: Operating System :: Microsoft :: Windows :: Windows 10
Classifier: License :: OSI Approved :: MIT License
Classifier: Programming Language :: Python :: 3
Requires-Python: >=3.6
License-File: LICENSE
Dynamic: author
Dynamic: author-email
Dynamic: classifier
Dynamic: description
Dynamic: keywords
Dynamic: license-file
Dynamic: requires-python
Dynamic: summary
